webpt/__init__.py
webpt/any.py
webpt/port_scanner.py
webpt/request_analysis.py
webpt/response_analysis.py
webpt/spider.py
webpt/subdomains.py
webpt/vuln.py
Webpt-2.3.1.dist-info/LICENSE
Webpt-2.3.1.dist-info/METADATA
Webpt-2.3.1.dist-info/WHEEL
Webpt-2.3.1.dist-info/top_level.txt
Webpt-2.3.1.dist-info/RECORD
