Metadata-Version: 2.1
Name: Webpt
Version: 2.3.1
Summary: Library for penetration testing, website analysis and requests.
Home-page: https://github.com/saharavitan/webpt
Author: Sahar Avitan
Author-email: avitansahar@gmail.com
License: UNKNOWN
Platform: UNKNOWN
Classifier: Programming Language :: Python :: 3
Classifier: License :: OSI Approved :: Apache Software License
Classifier: Operating System :: OS Independent
Requires-Python: >=3.8
Requires-Dist: requests
Requires-Dist: urllib3
